azure/mgmt/kubernetesconfiguration/__init__.py
azure/mgmt/kubernetesconfiguration/_configuration.py
azure/mgmt/kubernetesconfiguration/_serialization.py
azure/mgmt/kubernetesconfiguration/_source_control_configuration_client.py
azure/mgmt/kubernetesconfiguration/_version.py
azure/mgmt/kubernetesconfiguration/models.py
azure/mgmt/kubernetesconfiguration/py.typed
azure/mgmt/kubernetesconfiguration/aio/__init__.py
azure/mgmt/kubernetesconfiguration/aio/_configuration.py
azure/mgmt/kubernetesconfiguration/aio/_source_control_configuration_client.py
azure/mgmt/kubernetesconfiguration/v2020_07_01_preview/__init__.py
azure/mgmt/kubernetesconfiguration/v2020_07_01_preview/_configuration.py
azure/mgmt/kubernetesconfiguration/v2020_07_01_preview/_patch.py
azure/mgmt/kubernetesconfiguration/v2020_07_01_preview/_source_control_configuration_client.py
azure/mgmt/kubernetesconfiguration/v2020_07_01_preview/_vendor.py
azure/mgmt/kubernetesconfiguration/v2020_07_01_preview/_version.py
azure/mgmt/kubernetesconfiguration/v2020_07_01_preview/aio/__init__.py
azure/mgmt/kubernetesconfiguration/v2020_07_01_preview/aio/_configuration.py
azure/mgmt/kubernetesconfiguration/v2020_07_01_preview/aio/_patch.py
azure/mgmt/kubernetesconfiguration/v2020_07_01_preview/aio/_source_control_configuration_client.py
azure/mgmt/kubernetesconfiguration/v2020_07_01_preview/aio/operations/__init__.py
azure/mgmt/kubernetesconfiguration/v2020_07_01_preview/aio/operations/_extensions_operations.py
azure/mgmt/kubernetesconfiguration/v2020_07_01_preview/aio/operations/_operations.py
azure/mgmt/kubernetesconfiguration/v2020_07_01_preview/aio/operations/_patch.py
azure/mgmt/kubernetesconfiguration/v2020_07_01_preview/aio/operations/_source_control_configurations_operations.py
azure/mgmt/kubernetesconfiguration/v2020_07_01_preview/models/__init__.py
azure/mgmt/kubernetesconfiguration/v2020_07_01_preview/models/_models_py3.py
azure/mgmt/kubernetesconfiguration/v2020_07_01_preview/models/_patch.py
azure_mgmt_kubernetesconfiguration-3.1.0.dist-info/LICENSE
azure_mgmt_kubernetesconfiguration-3.1.0.dist-info/METADATA
azure_mgmt_kubernetesconfiguration-3.1.0.dist-info/WHEEL
azure_mgmt_kubernetesconfiguration-3.1.0.dist-info/top_level.txt
azure_mgmt_kubernetesconfiguration-3.1.0.dist-info/RECORD
